elevenlabs_cli_tool/__init__.py
elevenlabs_cli_tool/elevenlabsapi.py
elevenlabs_cli_tool/main.py
elevenlabs_cli_tool/templates.py
elevenlabs_cli_tool/utils.py
elevenlabs_cli_tool-0.1.6.dist-info/LICENSE.md
elevenlabs_cli_tool-0.1.6.dist-info/METADATA
elevenlabs_cli_tool-0.1.6.dist-info/WHEEL
elevenlabs_cli_tool-0.1.6.dist-info/entry_points.txt
elevenlabs_cli_tool-0.1.6.dist-info/RECORD
