Metadata-Version: 2.3
Name: elevenlabs-cli-tool
Version: 0.1.6
Summary: CLI tool to manage ElevenLabs conversational AI agents
Keywords: elevenlabs,cli,ai,conversational-ai,agents
Author: Angelo Giacco
Requires-Python: >=3.8,<4.0
Classifier: Development Status :: 3 - Alpha
Classifier: Intended Audience :: Developers
Classifier: License :: OSI Approved :: MIT License
Classifier: Operating System :: OS Independent
Classifier: Programming Language :: Python :: 3
Classifier: Programming Language :: Python :: 3.8
Classifier: Programming Language :: Python :: 3.9
Classifier: Programming Language :: Python :: 3.10
Classifier: Programming Language :: Python :: 3.11
Classifier: Programming Language :: Python :: 3.12
Classifier: Programming Language :: Python :: 3.13
Classifier: Topic :: Software Development :: Libraries :: Python Modules
Classifier: Topic :: Utilities
Requires-Dist: dotenv (>=0.9.9,<0.10.0)
Requires-Dist: elevenlabs (==2.3.0)
Requires-Dist: typer[all] (>=0.9.0,<0.10.0)
Project-URL: Homepage, https://github.com/angelogiacco/convai-cli
Project-URL: Repository, https://github.com/angelogiacco/convai-cli
